src/__init__.py
src/bidding_manager.py
bidd_Manager325-1.1.1.dist-info/LICENSE
bidd_Manager325-1.1.1.dist-info/METADATA
bidd_Manager325-1.1.1.dist-info/WHEEL
bidd_Manager325-1.1.1.dist-info/top_level.txt
bidd_Manager325-1.1.1.dist-info/RECORD
