Metadata-Version: 2.1
Name: bidd_Manager325
Version: 1.1.1
Summary: A brief description of your library
Home-page: https://github.com/yourusername/your_library
Author: Rahul
Author-email: rahulshirsat9156@gmail.com
License: MIT
Classifier: Programming Language :: Python :: 3
Classifier: License :: OSI Approved :: MIT License
Classifier: Operating System :: OS Independent
Requires-Python: >=3.6
License-File: LICENSE
